videosdk/plugins/turn_detector/__init__.py
videosdk/plugins/turn_detector/download_model.py
videosdk/plugins/turn_detector/model.py
videosdk/plugins/turn_detector/turn_detector.py
videosdk/plugins/turn_detector/turn_detector_v2.py
videosdk/plugins/turn_detector/turn_detector_v3.py
videosdk/plugins/turn_detector/version.py
videosdk_plugins_turn_detector-0.0.58.dist-info/METADATA
videosdk_plugins_turn_detector-0.0.58.dist-info/WHEEL
videosdk_plugins_turn_detector-0.0.58.dist-info/RECORD
